keva/__init__.py
Keva-1.0.dist-info/LICENSE
Keva-1.0.dist-info/METADATA
Keva-1.0.dist-info/WHEEL
Keva-1.0.dist-info/top_level.txt
Keva-1.0.dist-info/RECORD
