Metadata-Version: 2.1
Name: Keva
Version: 1.0
Summary: A python client for the Keva Database
Home-page: https://github.com/gugu256/gugu256
Author: gugu256
Author-email: gugu256@mail.com
License: MIT
Project-URL: Homepage, https://keva.pancakedev.repl.co
Keywords: database key value key-value KV
Classifier: Development Status :: 5 - Production/Stable
Classifier: Intended Audience :: Developers
Classifier: Programming Language :: Python :: 3
Classifier: Operating System :: Unix
Classifier: Operating System :: MacOS :: MacOS X
Classifier: Operating System :: Microsoft :: Windows
License-File: LICENSE
Requires-Dist: requests
